__init__.py
brdata_rag_tools/__init__.py
brdata_rag_tools/databases.py
brdata_rag_tools/datastructures.py
brdata_rag_tools/embeddings.py
brdata_rag_tools/models.py
brdata_rag_tools-0.1.5.2.dist-info/LICENSE
brdata_rag_tools-0.1.5.2.dist-info/METADATA
brdata_rag_tools-0.1.5.2.dist-info/WHEEL
brdata_rag_tools-0.1.5.2.dist-info/top_level.txt
brdata_rag_tools-0.1.5.2.dist-info/RECORD
